flake8_typing_collections/__init__.py
flake8_typing_collections/ast_import_decode.py
flake8_typing_collections/checker.py
flake8_typing_collections-2.1.dist-info/LICENSE
flake8_typing_collections-2.1.dist-info/METADATA
flake8_typing_collections-2.1.dist-info/WHEEL
flake8_typing_collections-2.1.dist-info/entry_points.txt
flake8_typing_collections-2.1.dist-info/top_level.txt
flake8_typing_collections-2.1.dist-info/RECORD
